{
    "codeToName": {
        "32": "uni0020",
        "33": "uni0021",
        "34": "uni0022",
        "35": "uni0023",
        "36": "uni0024",
        "37": "uni0025",
        "38": "uni0026",
        "39": "uni0027",
        "40": "uni0028",
        "41": "uni0029",
        "42": "uni002a",
        "43": "uni002b",
        "44": "uni002c",
        "45": "uni002d",
        "46": "uni002e",
        "47": "uni002f",
        "48": "uni0030",
        "49": "uni0031",
        "50": "uni0032",
        "51": "uni0033",
        "52": "uni0034",
        "53": "uni0035",
        "54": "uni0036",
        "55": "uni0037",
        "56": "uni0038",
        "57": "uni0039",
        "58": "uni003a",
        "59": "uni003b",
        "60": "uni003c",
        "61": "uni003d",
        "62": "uni003e",
        "63": "uni003f",
        "64": "uni0040",
        "65": "uni0041",
        "66": "uni0042",
        "67": "uni0043",
        "68": "uni0044",
        "69": "uni0045",
        "70": "uni0046",
        "71": "uni0047",
        "72": "uni0048",
        "73": "uni0049",
        "74": "uni004a",
        "75": "uni004b",
        "76": "uni004c",
        "77": "uni004d",
        "78": "uni004e",
        "79": "uni004f",
        "80": "uni0050",
        "81": "uni0051",
        "82": "uni0052",
        "83": "uni0053",
        "84": "uni0054",
        "85": "uni0055",
        "86": "uni0056",
        "87": "uni0057",
        "88": "uni0058",
        "89": "uni0059",
        "90": "uni005a",
        "91": "uni005b",
        "92": "uni005c",
        "93": "uni005d",
        "94": "uni005e",
        "95": "uni005f",
        "96": "uni0060",
        "97": "uni0061",
        "98": "uni0062",
        "99": "uni0063",
        "100": "uni0064",
        "101": "uni0065",
        "102": "uni0066",
        "103": "uni0067",
        "104": "uni0068",
        "105": "uni0069",
        "106": "uni006a",
        "107": "uni006b",
        "108": "uni006c",
        "109": "uni006d",
        "110": "uni006e",
        "111": "uni006f",
        "112": "uni0070",
        "113": "uni0071",
        "114": "uni0072",
        "115": "uni0073",
        "116": "uni0074",
        "117": "uni0075",
        "118": "uni0076",
        "119": "uni0077",
        "120": "uni0078",
        "121": "uni0079",
        "122": "uni007a",
        "123": "uni007b",
        "124": "uni007c",
        "125": "uni007d",
        "126": "uni007e",
        "165": "uni00a5",
        "176": "uni00b0",
        "183": "uni00b7",
        "2547": "uni09f3",
        "8211": "uni2013",
        "8212": "uni2014",
        "8226": "uni2022",
        "8230": "uni2026",
        "12289": "uni3001",
        "12290": "uni3002",
        "12300": "uni300c",
        "12301": "uni300d",
        "12304": "uni3010",
        "12305": "uni3011",
        "19996": "uni4e1c",
        "19997": "uni4e1d",
        "20013": "uni4e2d",
        "20061": "uni4e5d",
        "20113": "uni4e91",
        "21019": "uni521b",
        "21306": "uni533a",
        "22253": "uni56ed",
        "22320": "uni5730",
        "22484": "uni57d4",
        "22823": "uni5927",
        "24030": "uni5dde",
        "24066": "uni5e02",
        "24191": "uni5e7f",
        "24515": "uni5fc3",
        "25151": "uni623f",
        "26635": "uni680b",
        "28023": "uni6d77",
        "30465": "uni7701",
        "30693": "uni77e5",
        "32511": "uni7eff",
        "35782": "uni8bc6",
        "36947": "uni9053",
        "40644": "uni9ec4",
        "40857": "uni9f99",
        "65288": "uniff08",
        "65289": "uniff09",
        "65292": "uniff0c",
        "65306": "uniff1a",
        "65307": "uniff1b"
    },
    "isUnicode": true,
    "EncodingScheme": "FontSpecific",
    "FontName": "Arial Unicode MS",
    "FullName": "Arial Unicode MS",
    "Version": "Version 1.01",
    "PostScriptName": "ArialUnicodeMS",
    "Weight": "Medium",
    "ItalicAngle": "0",
    "IsFixedPitch": "false",
    "UnderlineThickness": "50",
    "UnderlinePosition": "-100",
    "FontHeightOffset": "0",
    "Ascender": "1069",
    "Descender": "-271",
    "FontBBox": [
        "-1011",
        "-330",
        "2260",
        "1078"
    ],
    "StartCharMetrics": "165",
    "C": {
        "32": 278,
        "33": 278,
        "34": 355,
        "35": 556,
        "36": 556,
        "37": 889,
        "38": 667,
        "39": 191,
        "40": 333,
        "41": 333,
        "42": 389,
        "43": 584,
        "44": 278,
        "45": 333,
        "46": 278,
        "47": 278,
        "48": 556,
        "49": 556,
        "50": 556,
        "51": 556,
        "52": 556,
        "53": 556,
        "54": 556,
        "55": 556,
        "56": 556,
        "57": 556,
        "58": 278,
        "59": 278,
        "60": 584,
        "61": 584,
        "62": 584,
        "63": 556,
        "64": 1015,
        "65": 667,
        "66": 667,
        "67": 722,
        "68": 722,
        "69": 667,
        "70": 611,
        "71": 778,
        "72": 722,
        "73": 278,
        "74": 500,
        "75": 667,
        "76": 556,
        "77": 833,
        "78": 722,
        "79": 778,
        "80": 667,
        "81": 778,
        "82": 722,
        "83": 667,
        "84": 611,
        "85": 722,
        "86": 667,
        "87": 944,
        "88": 667,
        "89": 667,
        "90": 611,
        "91": 278,
        "92": 278,
        "93": 278,
        "94": 469,
        "95": 500,
        "96": 333,
        "97": 556,
        "98": 556,
        "99": 500,
        "100": 556,
        "101": 556,
        "102": 278,
        "103": 556,
        "104": 556,
        "105": 222,
        "106": 222,
        "107": 500,
        "108": 222,
        "109": 833,
        "110": 556,
        "111": 556,
        "112": 556,
        "113": 556,
        "114": 333,
        "115": 500,
        "116": 278,
        "117": 556,
        "118": 500,
        "119": 722,
        "120": 500,
        "121": 500,
        "122": 500,
        "123": 334,
        "124": 260,
        "125": 334,
        "126": 584,
        "165": 556,
        "176": 400,
        "183": 278,
        "2547": 567,
        "8211": 500,
        "8212": 1000,
        "8226": 350,
        "8230": 1000,
        "12289": 1000,
        "12290": 1000,
        "12300": 1000,
        "12301": 1000,
        "12304": 1000,
        "12305": 1000,
        "19996": 1000,
        "19997": 1000,
        "20013": 1000,
        "20061": 1000,
        "20113": 1000,
        "21019": 1000,
        "21306": 1000,
        "22253": 1000,
        "22320": 1000,
        "22484": 1000,
        "22823": 1000,
        "24030": 1000,
        "24066": 1000,
        "24191": 1000,
        "24515": 1000,
        "25151": 1000,
        "26635": 1000,
        "28023": 1000,
        "30465": 1000,
        "30693": 1000,
        "32511": 1000,
        "35782": 1000,
        "36947": 1000,
        "40644": 1000,
        "40857": 1000,
        "65288": 1000,
        "65289": 1000,
        "65292": 1000,
        "65306": 1000,
        "65307": 1000
    },
    "CIDtoGID_Compressed": true,
    "CIDtoGID": "eJztz9VuXTEURdFVZmZmZmZmZmbmDygzM35vq7R9iBQlqXJznaRjvGwdH8ueTpqoXdqnQzqmUzqnS7qmW7qnR3qmV3qnT\/qmX\/pnQAZmUAZnSIZmWIZnREZmVEZnTMZmXMZnQiZmUiZnSqZmWqZnRmZmVmZnTuZmXuZnQRZmURZnSZZmWZZnRVZmVVZnTdZmXdZnQzZmUzZnS7ZmW7ZnR3ZmV3ZnT\/ZmX\/bnQA7mUA7nSI7mWI7nRE7mVE7nTFMfX8vZOlfP1fo6X9EbAQAAAOC3C6UDAAAAAAAAAAAAAICquZhL9fy9\/GdeqUYKAAAAAAAAAFCHq7lWx+r13KiZN3OrujkAAAAAAAAAAAAAAAAAAMA\/e5CHDex41MwFj5v5\/L+eVOkeAGjpnpYOoBV7VjoAANqs56UDarwoHdBGvCwdAA16VToAAKBNe12hc95U6JzW523pAPjlXekAgCp7XzoAAADIh9IBAABQAR9LBwAAAABAlX0qHUBFfC4dAAAAQIv1pXQAAAAAAABAm\/a1dAAAQIvxrXQAAAAAAAAAQKN9Lx1AI\/0oHQAAAAAAAAAAAAAAAAAAAAAAAAAAAAAAAAAAAAAAAAAAAAAAAAAAAAAAAAAAAAAA8F+4nTs18249e+7lfnViaG4\/Ac1EJ00=",
    "_version_": 6
}